{
  "-1": {
    "MMR": [
      "black",
      0.05515148582100319,
      "amp",
      0.045439532898162056,
      "join",
      0.025580899835012442,
      "today",
      0.02492017308780411,
      "community",
      0.023527743930094366,
      "police",
      0.02338727340677552,
      "justice",
      0.019087357666183316,
      "women",
      0.015231908484723944,
      "violence",
      0.014092256240901827,
      "vote",
      0.012472241628409804
    ],
    "Llama2": [
      "Black Community Safety and Justice",
      1.0,
      "",
      0.0,
      "",
      0.0,
      "",
      0.0,
      "",
      0.0,
      "",
      0.0,
      "",
      0.0,
      "",
      0.0,
      "",
      0.0,
      "",
      0.0
    ],
    "KeyBERT": [
      "vote",
      0.7173820734024048,
      "voting",
      0.7148083448410034,
      "blacklivesmatter",
      0.7089783549308777,
      "racism",
      0.6992684602737427,
      "community",
      0.6988433599472046,
      "communities",
      0.6919318437576294,
      "members",
      0.6813141107559204,
      "blm",
      0.6799371242523193,
      "racial",
      0.6789518594741821,
      "action",
      0.6778197288513184
    ],
    "Main": [
      "black",
      0.05515148582100319,
      "amp",
      0.045439532898162056,
      "us",
      0.04285300325242688,
      "people",
      0.032500678876285556,
      "join",
      0.025580899835012442,
      "today",
      0.02492017308780411,
      "community",
      0.023527743930094366,
      "police",
      0.02338727340677552,
      "support",
      0.020323118414757008,
      "justice",
      0.019087357666183316
    ]
  }
}